rschip/__init__.py
rschip/image_chip.py
rschip/remove_background_only.py
rschip/segmentation_mask.py
rschip-0.3.1.dist-info/LICENSE
rschip-0.3.1.dist-info/METADATA
rschip-0.3.1.dist-info/WHEEL
rschip-0.3.1.dist-info/top_level.txt
rschip-0.3.1.dist-info/RECORD
