Metadata-Version: 2.1
Name: rschip
Version: 0.3.1
Summary: Prepare satellite images and training data for use with deep learning models
Author-email: Tom Wilson <thomaswilson81@gmail.com>
License: MIT
Keywords: satellite,deep learning,tiling,segmentation,geospatial
Classifier: Development Status :: 3 - Alpha
Classifier: Intended Audience :: Developers
Classifier: Intended Audience :: Science/Research
Classifier: License :: OSI Approved :: MIT License
Classifier: Programming Language :: Python :: 3
Classifier: Programming Language :: Python :: 3.6
Classifier: Programming Language :: Python :: 3.7
Classifier: Programming Language :: Python :: 3.8
Classifier: Programming Language :: Python :: 3.9
Classifier: Programming Language :: Python :: 3.10
Classifier: Programming Language :: Python :: 3.11
Classifier: Programming Language :: Python :: 3.12
Classifier: Programming Language :: Python :: 3.13
Classifier: Topic :: Scientific/Engineering :: GIS
Classifier: Topic :: Software Development :: Libraries :: Python Modules
Requires-Python: >=3.6
License-File: LICENSE
Requires-Dist: rasterio
Requires-Dist: numpy
Requires-Dist: geopandas
Requires-Dist: shapely
Provides-Extra: lint
Requires-Dist: flake8; extra == "lint"
Requires-Dist: black; extra == "lint"
Provides-Extra: test
Requires-Dist: pytest; extra == "test"
